emucore_direct/__init__.py
emucore_direct/client.py
emucore_direct/emucore_pb2.py
emucore_direct/emucore_pb2_grpc.py
emucore_direct/types.py
emucore_direct/utils.py
emucore_direct-1.0.7.dist-info/METADATA
emucore_direct-1.0.7.dist-info/WHEEL
emucore_direct-1.0.7.dist-info/top_level.txt
emucore_direct-1.0.7.dist-info/RECORD
